aws_secrets_manager/__init__.py
aws_secrets_manager/manager.py
aws_secrets_manager-0.0.1.dist-info/METADATA
aws_secrets_manager-0.0.1.dist-info/WHEEL
aws_secrets_manager-0.0.1.dist-info/top_level.txt
aws_secrets_manager-0.0.1.dist-info/RECORD
